{
  "pages": [
    // pages数组中第一项表示应用启动页，参考：https://uniapp.dcloud.io/collocation/pages
    {
      "path": "pages/index/index",
      "style": {
        "navigationBarTitleText": "uniapp-vue3"
      }
    },
    {
      "path": "pages/font/index",
      "style": {
        "navigationBarTitleText": "font"
      }
    },
    {
      "path": "pages/size/index",
      "style": {
        "navigationBarTitleText": "size"
      }
    },
    {
      "path": "pages/shadow/index",
      "style": {
        "navigationBarTitleText": "shadow"
      }
    },
    {
      "path": "pages/border/index",
      "style": {
        "navigationBarTitleText": "border"
      }
    },
    {
      "path": "pages/spacing/index",
      "style": {
        "navigationBarTitleText": "spacing"
      }
    },
    {
      "path": "pages/shortcuts/index",
      "style": {
        "navigationBarTitleText": "shortcuts"
      }
    },
    {
      "path": "pages/class/index",
      "style": {
        "navigationBarTitleText": ":class"
      }
    },
    {
      "path": "pages/color/index",
      "style": {
        "navigationBarTitleText": "color"
      }
    },
    {
      "path": "pages/attributify-mode/index",
      "style": {
        "navigationBarTitleText": "attributify-mode"
      }
    },
    {
      "path": "pages/animation/index",
      "style": {
        "navigationBarTitleText": "animation"
      }
    },
    {
      "path": "pages/bg/index",
      "style": {
        "navigationBarTitleText": "bg"
      }
    },
    {
      "path": "pages/odd-even/index",
      "style": {
        "navigationBarTitleText": "odd-even"
      }
    },
    {
      "path": "pages/first-last/index",
      "style": {
        "navigationBarTitleText": "first-last"
      }
    },
    {
      "path": "pages/divide/index",
      "style": {
        "navigationBarTitleText": "divide"
      }
    },
    {
      "path": "pages/space/index",
      "style": {
        "navigationBarTitleText": "space"
      }
    },
    {
      "path": "pages/apply/index",
      "style": {
        "navigationBarTitleText": "apply"
      }
    }
  ],
  "globalStyle": {
    "navigationBarTextStyle": "black",
    "navigationBarTitleText": "uni-app",
    "navigationBarBackgroundColor": "#F8F8F8",
    "backgroundColor": "#F8F8F8"
  }
}
